{
  "protocol_version" : "0.0.6",
  "configuration" : {
    "version" : "(6.13.0) (explicit/395ca54e)",
    "tlc" : "normal",
    "sigsgev" : "altstack",
    "notifications" : "kqueue",
    "architecture" : "amd64",
    "disabled_features" : "com,shared_perfcounters",
    "smallconfig" : "disabled",
    "bigarrays" : "disabled",
    "softdebug" : "enabled",
    "interpreter" : "enabled",
    "llvm_support" : "disabled",
    "suspend" : "preemptive"
  },
  "memory" : {
    "Resident Size" : "2300690432",
    "Virtual Size" : "38725832704",
    "minor_gc_time" : "0",
    "major_gc_time" : "19719066",
    "minor_gc_count" : "0",
    "major_gc_count" : "55",
    "major_gc_time_concurrent" : "0"
 },
  "threads" : [
 {
    "is_managed" : false,
    "offset_free_hash" : "0x0",
    "offset_rich_hash" : "0x0",
    "crashed" : false,
    "native_thread_id" : "0x70000d3b3000",
    "thread_info_addr" : "0x7fae23440000",
    "thread_name" : "tid_22517",
    "ctx" : {
      "IP" : "0x7ff81ddc73ea",
      "SP" : "0x70000d3b2cb8",
      "BP" : "0x70000d3b2d60"
  },
    "unmanaged_frames" : [
  {
      "is_managed" : "false",
      "native_address" : "0x15f3a8286",
      "native_offset" : "0x00000"
   }
,
  {
      "is_managed" : "false",
      "native_address" : "0x15f501378",
      "native_offset" : "0x00000"
   }
,
  {
      "is_managed" : "false",
      "native_address" : "0x15f5016b2",
      "native_offset" : "0x00000"
   }
,
  {
      "is_managed" : "false",
      "native_address" : "0x15f501469",
      "native_offset" : "0x00000"
   }
,
  {
      "is_managed" : "false",
      "native_address" : "0x15f405b4d",
      "native_offset" : "0x00000"
   }
,
  {
      "is_managed" : "false",
      "native_address" : "0x7ff81de16dfd",
      "native_offset" : "0x00000"
   }
,
  {
      "is_managed" : "false",
      "native_address" : "unregistered"
   }
,
  {
      "is_managed" : "false",
      "native_address" : "0x15f54fecc",
      "native_offset" : "0x00000"
   }
,
  {
      "is_managed" : "false",
      "native_address" : "0x15f559e9a",
      "native_offset" : "0x00000"
   }
,
  {
      "is_managed" : "false",
      "native_address" : "0x15f459f36",
      "native_offset" : "0x00000"
   }
,
  {
      "is_managed" : "false",
      "native_address" : "0x15f5020c0",
      "native_offset" : "0x00000"
   }
,
  {
      "is_managed" : "false",
      "native_address" : "0x15f501f65",
      "native_offset" : "0x00000"
   }
,
  {
      "is_managed" : "false",
      "native_address" : "0x15f57f319",
      "native_offset" : "0x00000"
   }
,
  {
      "is_managed" : "false",
      "native_address" : "0x15f57f2b1",
      "native_offset" : "0x00000"
   }
,
  {
      "is_managed" : "false",
      "native_address" : "0x7ff81de014e1",
      "native_offset" : "0x00000"
   }
,
  {
      "is_managed" : "false",
      "native_address" : "0x7ff81ddfcf6b",
      "native_offset" : "0x00000"
   }

  ]
 },
 {
    "is_managed" : true,
    "offset_free_hash" : "0xbaa0c96f5",
    "offset_rich_hash" : "0xbaa0c9ab6",
    "crashed" : false,
    "native_thread_id" : "0x70000e03f000",
    "thread_info_addr" : "0x7fae3e643800",
    "thread_name" : "Burst-CompilerThread-2",
    "ctx" : {
      "IP" : "0x7ff81ddc73ea",
      "SP" : "0x70000e03dbb8",
      "BP" : "0x70000e03dc60"
  },
    "managed_frames" : [
  {
      "is_managed" : "false",
      "native_address" : "unregistered"
   }
,
  {
      "is_managed" : "true",
      "guid" : "5B93611B-6FF0-4343-9D40-3FBB0837BC10",
      "token" : "0x00000",
      "native_offset" : "0x0",
      "filename" : "mscorlib.dll",
      "sizeofimage" : "0x470000",
      "timestamp" : "0xcdd9381c",
      "il_offset" : "0x00000"
   }
,
  {
      "is_managed" : "true",
      "guid" : "5B93611B-6FF0-4343-9D40-3FBB0837BC10",
      "token" : "0x60020b3",
      "native_offset" : "0x0",
      "filename" : "mscorlib.dll",
      "sizeofimage" : "0x470000",
      "timestamp" : "0xcdd9381c",
      "il_offset" : "0x000c7"
   }
,
  {
      "is_managed" : "true",
      "guid" : "5B93611B-6FF0-4343-9D40-3FBB0837BC10",
      "token" : "0x60020a5",
      "native_offset" : "0x0",
      "filename" : "mscorlib.dll",
      "sizeofimage" : "0x470000",
      "timestamp" : "0xcdd9381c",
      "il_offset" : "0x000a1"
   }
,
  {
      "is_managed" : "true",
      "guid" : "5B93611B-6FF0-4343-9D40-3FBB0837BC10",
      "token" : "0x60020a9",
      "native_offset" : "0x0",
      "filename" : "mscorlib.dll",
      "sizeofimage" : "0x470000",
      "timestamp" : "0xcdd9381c",
      "il_offset" : "0x00000"
   }
,
  {
      "is_managed" : "true",
      "guid" : "56B59C73-3E00-4375-8D92-23398C020E5C",
      "token" : "0x6003ffa",
      "native_offset" : "0x0",
      "filename" : "System.dll",
      "sizeofimage" : "0x29a000",
      "timestamp" : "0xb03d23c3",
      "il_offset" : "0x0006e"
   }
,
  {
      "is_managed" : "true",
      "guid" : "56B59C73-3E00-4375-8D92-23398C020E5C",
      "token" : "0x6003ff9",
      "native_offset" : "0x0",
      "filename" : "System.dll",
      "sizeofimage" : "0x29a000",
      "timestamp" : "0xb03d23c3",
      "il_offset" : "0x0003c"
   }
,
  {
      "is_managed" : "true",
      "guid" : "56B59C73-3E00-4375-8D92-23398C020E5C",
      "token" : "0x6003ff4",
      "native_offset" : "0x0",
      "filename" : "System.dll",
      "sizeofimage" : "0x29a000",
      "timestamp" : "0xb03d23c3",
      "il_offset" : "0x00000"
   }
,
  {
      "is_managed" : "true",
      "guid" : "A2DD1524-8A25-411E-914A-F2A2C82FB63F",
      "token" : "0x6000b35",
      "native_offset" : "0x0",
      "filename" : "Burst.Compiler.IL.dll",
      "sizeofimage" : "0x188000",
      "timestamp" : "0xe06db050",
      "il_offset" : "0x00024"
   }
,
  {
      "is_managed" : "true",
      "guid" : "A2DD1524-8A25-411E-914A-F2A2C82FB63F",
      "token" : "0x6000b9c",
      "native_offset" : "0x0",
      "filename" : "Burst.Compiler.IL.dll",
      "sizeofimage" : "0x188000",
      "timestamp" : "0xe06db050",
      "il_offset" : "0x0006e"
   }
,
  {
      "is_managed" : "true",
      "guid" : "5B93611B-6FF0-4343-9D40-3FBB0837BC10",
      "token" : "0x6001f7d",
      "native_offset" : "0x0",
      "filename" : "mscorlib.dll",
      "sizeofimage" : "0x470000",
      "timestamp" : "0xcdd9381c",
      "il_offset" : "0x00014"
   }
,
  {
      "is_managed" : "true",
      "guid" : "5B93611B-6FF0-4343-9D40-3FBB0837BC10",
      "token" : "0x6001f25",
      "native_offset" : "0x0",
      "filename" : "mscorlib.dll",
      "sizeofimage" : "0x470000",
      "timestamp" : "0xcdd9381c",
      "il_offset" : "0x00071"
   }
,
  {
      "is_managed" : "true",
      "guid" : "5B93611B-6FF0-4343-9D40-3FBB0837BC10",
      "token" : "0x6001f23",
      "native_offset" : "0x0",
      "filename" : "mscorlib.dll",
      "sizeofimage" : "0x470000",
      "timestamp" : "0xcdd9381c",
      "il_offset" : "0x00000"
   }
,
  {
      "is_managed" : "true",
      "guid" : "5B93611B-6FF0-4343-9D40-3FBB0837BC10",
      "token" : "0x6001f22",
      "native_offset" : "0x0",
      "filename" : "mscorlib.dll",
      "sizeofimage" : "0x470000",
      "timestamp" : "0xcdd9381c",
      "il_offset" : "0x0002b"
   }
,
  {
      "is_managed" : "true",
      "guid" : "5B93611B-6FF0-4343-9D40-3FBB0837BC10",
      "token" : "0x6001f7f",
      "native_offset" : "0x0",
      "filename" : "mscorlib.dll",
      "sizeofimage" : "0x470000",
      "timestamp" : "0xcdd9381c",
      "il_offset" : "0x00008"
   }
,
  {
      "is_managed" : "true",
      "guid" : "5B93611B-6FF0-4343-9D40-3FBB0837BC10",
      "token" : "0x00000",
      "native_offset" : "0x0",
      "filename" : "mscorlib.dll",
      "sizeofimage" : "0x470000",
      "timestamp" : "0xcdd9381c",
      "il_offset" : "0x00065"
   }

  ],
  "unmanaged_frames" : [
 {
    "is_managed" : "false",
    "native_address" : "0x15f3a8286",
    "native_offset" : "0x00000"
  }
,
 {
    "is_managed" : "false",
    "native_address" : "0x15f501378",
    "native_offset" : "0x00000"
  }
,
 {
    "is_managed" : "false",
    "native_address" : "0x15f5016b2",
    "native_offset" : "0x00000"
  }
,
 {
    "is_managed" : "false",
    "native_address" : "0x15f501469",
    "native_offset" : "0x00000"
  }
,
 {
    "is_managed" : "false",
    "native_address" : "0x15f405b4d",
    "native_offset" : "0x00000"
  }
,
 {
    "is_managed" : "false",
    "native_address" : "0x7ff81de16dfd",
    "native_offset" : "0x00000"
  }
,
 {
    "is_managed" : "false",
    "native_address" : "0x7fae39ced7f0",
    "native_offset" : "0x00000"
  }
,
 {
    "is_managed" : "false",
    "native_address" : "0x15f54fee8",
    "native_offset" : "0x00000"
  }
,
 {
    "is_managed" : "false",
    "native_address" : "0x15f50cd08",
    "native_offset" : "0x00000"
  }
,
 {
    "is_managed" : "false",
    "native_address" : "0x15f50c9ae",
    "native_offset" : "0x00000"
  }
,
 {
    "is_managed" : "false",
    "native_address" : "0x15f4fcb9a",
    "native_offset" : "0x00000"
  }
,
 {
    "is_managed" : "false",
    "native_address" : "0x15f4a7dca",
    "native_offset" : "0x00000"
  }
,
 {
    "is_managed" : "true",
    "guid" : "5B93611B-6FF0-4343-9D40-3FBB0837BC10",
    "token" : "0x00000",
    "native_offset" : "0x0",
    "filename" : "mscorlib.dll",
    "sizeofimage" : "0x470000",
    "timestamp" : "0xcdd9381c",
    "il_offset" : "0x00000"
  }
,
 {
    "is_managed" : "true",
    "guid" : "5B93611B-6FF0-4343-9D40-3FBB0837BC10",
    "token" : "0x60020a5",
    "native_offset" : "0x0",
    "filename" : "mscorlib.dll",
    "sizeofimage" : "0x470000",
    "timestamp" : "0xcdd9381c",
    "il_offset" : "0x00000"
  }

 ]
},
{
  "is_managed" : true,
  "offset_free_hash" : "0xbaa0c96f5",
  "offset_rich_hash" : "0xbaa0c9ab6",
  "crashed" : false,
  "native_thread_id" : "0x70000de3c000",
  "thread_info_addr" : "0x7fae3e58ae00",
  "thread_name" : "Burst-CompilerThread-1",
  "ctx" : {
    "IP" : "0x7ff81ddc73ea",
    "SP" : "0x70000de3abb8",
    "BP" : "0x70000de3ac60"
 },
  "managed_frames" : [
 {
    "is_managed" : "false",
    "native_address" : "unregistered"
  }
,
 {
    "is_managed" : "true",
    "guid" : "5B93611B-6FF0-4343-9D40-3FBB0837BC10",
    "token" : "0x00000",
    "native_offset" : "0x0",
    "filename" : "mscorlib.dll",
    "sizeofimage" : "0x470000",
    "timestamp" : "0xcdd9381c",
    "il_offset" : "0x00000"
  }
,
 {
    "is_managed" : "true",
    "guid" : "5B93611B-6FF0-4343-9D40-3FBB0837BC10",
    "token" : "0x60020b3",
    "native_offset" : "0x0",
    "filename" : "mscorlib.dll",
    "sizeofimage" : "0x470000",
    "timestamp" : "0xcdd9381c",
    "il_offset" : "0x000c7"
  }
,
 {
    "is_managed" : "true",
    "guid" : "5B93611B-6FF0-4343-9D40-3FBB0837BC10",
    "token" : "0x60020a5",
    "native_offset" : "0x0",
    "filename" : "mscorlib.dll",
    "sizeofimage" : "0x470000",
    "timestamp" : "0xcdd9381c",
    "il_offset" : "0x000a1"
  }
,
 {
    "is_managed" : "true",
    "guid" : "5B93611B-6FF0-4343-9D40-3FBB0837BC10",
    "token" : "0x60020a9",
    "native_offset" : "0x0",
    "filename" : "mscorlib.dll",
    "sizeofimage" : "0x470000",
    "timestamp" : "0xcdd9381c",
    "il_offset" : "0x00000"
  }
,
 {
    "is_managed" : "true",
    "guid" : "56B59C73-3E00-4375-8D92-23398C020E5C",
    "token" : "0x6003ffa",
    "native_offset" : "0x0",
    "filename" : "System.dll",
    "sizeofimage" : "0x29a000",
    "timestamp" : "0xb03d23c3",
    "il_offset" : "0x0006e"
  }
,
 {
    "is_managed" : "true",
    "guid" : "56B59C73-3E00-4375-8D92-23398C020E5C",
    "token" : "0x6003ff9",
    "native_offset" : "0x0",
    "filename" : "System.dll",
    "sizeofimage" : "0x29a000",
    "timestamp" : "0xb03d23c3",
    "il_offset" : "0x0003c"
  }
,
 {
    "is_managed" : "true",
    "guid" : "56B59C73-3E00-4375-8D92-23398C020E5C",
    "token" : "0x6003ff4",
    "native_offset" : "0x0",
    "filename" : "System.dll",
    "sizeofimage" : "0x29a000",
    "timestamp" : "0xb03d23c3",
    "il_offset" : "0x00000"
  }
,
 {
    "is_managed" : "true",
    "guid" : "A2DD1524-8A25-411E-914A-F2A2C82FB63F",
    "token" : "0x6000b35",
    "native_offset" : "0x0",
    "filename" : "Burst.Compiler.IL.dll",
    "sizeofimage" : "0x188000",
    "timestamp" : "0xe06db050",
    "il_offset" : "0x00024"
  }
,
 {
    "is_managed" : "true",
    "guid" : "A2DD1524-8A25-411E-914A-F2A2C82FB63F",
    "token" : "0x6000b9c",
    "native_offset" : "0x0",
    "filename" : "Burst.Compiler.IL.dll",
    "sizeofimage" : "0x188000",
    "timestamp" : "0xe06db050",
    "il_offset" : "0x0006e"
  }
,
 {
    "is_managed" : "true",
    "guid" : "5B93611B-6FF0-4343-9D40-3FBB0837BC10",
    "token" : "0x6001f7d",
    "native_offset" : "0x0",
    "filename" : "mscorlib.dll",
    "sizeofimage" : "0x470000",
    "timestamp" : "0xcdd9381c",
    "il_offset" : "0x00014"
  }
,
 {
    "is_managed" : "true",
    "guid" : "5B93611B-6FF0-4343-9D40-3FBB0837BC10",
    "token" : "0x6001f25",
    "native_offset" : "0x0",
    "filename" : "mscorlib.dll",
    "sizeofimage" : "0x470000",
    "timestamp" : "0xcdd9381c",
    "il_offset" : "0x00071"
  }
,
 {
    "is_managed" : "true",
    "guid" : "5B93611B-6FF0-4343-9D40-3FBB0837BC10",
    "token" : "0x6001f23",
    "native_offset" : "0x0",
    "filename" : "mscorlib.dll",
    "sizeofimage" : "0x470000",
    "timestamp" : "0xcdd9381c",
    "il_offset" : "0x00000"
  }
,
 {
    "is_managed" : "true",
    "guid" : "5B93611B-6FF0-4343-9D40-3FBB0837BC10",
    "token" : "0x6001f22",
    "native_offset" : "0x0",
    "filename" : "mscorlib.dll",
    "sizeofimage" : "0x470000",
    "timestamp" : "0xcdd9381c",
    "il_offset" : "0x0002b"
  }
,
 {
    "is_managed" : "true",
    "guid" : "5B93611B-6FF0-4343-9D40-3FBB0837BC10",
    "token" : "0x6001f7f",
    "native_offset" : "0x0",
    "filename" : "mscorlib.dll",
    "sizeofimage" : "0x470000",
    "timestamp" : "0xcdd9381c",
    "il_offset" : "0x00008"
  }
,
 {
    "is_managed" : "true",
    "guid" : "5B93611B-6FF0-4343-9D40-3FBB0837BC10",
    "token" : "0x00000",
    "native_offset" : "0x0",
    "filename" : "mscorlib.dll",
    "sizeofimage" : "0x470000",
    "timestamp" : "0xcdd9381c",
    "il_offset" : "0x00065"
  }

 ],
"unmanaged_frames" : [
{
  "is_managed" : "false",
  "native_address" : "0x15f3a8286",
  "native_offset" : "0x00000"
 }
,
{
  "is_managed" : "false",
  "native_address" : "0x15f501378",
  "native_offset" : "0x00000"
 }
,
{
  "is_managed" : "false",
  "native_address" : "0x15f5016b2",
  "native_offset" : "0x00000"
 }
,
{
  "is_managed" : "false",
  "native_address" : "0x15f501469",
  "native_offset" : "0x00000"
 }
,
{
  "is_managed" : "false",
  "native_address" : "0x15f405b4d",
  "native_offset" : "0x00000"
 }
,
{
  "is_managed" : "false",
  "native_address" : "0x7ff81de16dfd",
  "native_offset" : "0x00000"
 }
,
{
  "is_managed" : "false",
  "native_address" : "0x7fae39cd6d60",
  "native_offset" : "0x00000"
 }
,
{
  "is_managed" : "false",
  "native_address" : "0x15f54fee8",
  "native_offset" : "0x00000"
 }
,
{
  "is_managed" : "false",
  "native_address" : "0x15f50cd08",
  "native_offset" : "0x00000"
 }
,
{
  "is_managed" : "false",
  "native_address" : "0x15f50c9ae",
  "native_offset" : "0x00000"
 }
,
{
  "is_managed" : "false",
  "native_address" : "0x15f4fcb9a",
  "native_offset" : "0x00000"
 }
,
{
  "is_managed" : "false",
  "native_address" : "0x15f4a7dca",
  "native_offset" : "0x00000"
 }
,
{
  "is_managed" : "true",
  "guid" : "5B93611B-6FF0-4343-9D40-3FBB0837BC10",
  "token" : "0x00000",
  "native_offset" : "0x0",
  "filename" : "mscorlib.dll",
  "sizeofimage" : "0x470000",
  "timestamp" : "0xcdd9381c",
  "il_offset" : "0x00000"
 }
,
{
  "is_managed" : "true",
  "guid" : "5B93611B-6FF0-4343-9D40-3FBB0837BC10",
  "token" : "0x60020a5",
  "native_offset" : "0x0",
  "filename" : "mscorlib.dll",
  "sizeofimage" : "0x470000",
  "timestamp" : "0xcdd9381c",
  "il_offset" : "0x00000"
 }

]
},
{
"is_managed" : true,
"offset_free_hash" : "0xeec5a6bfb",
"offset_rich_hash" : "0xeec5a6f81",
"crashed" : false,
"native_thread_id" : "0x70000ec51000",
"thread_info_addr" : "0x7fae3ecb6a00",
"thread_name" : "Burst-ProgressReporter",
"ctx" : {
  "IP" : "0x7ff81ddc73ea",
  "SP" : "0x70000ec50218",
  "BP" : "0x70000ec502c0"
},
"managed_frames" : [
{
  "is_managed" : "false",
  "native_address" : "unregistered"
 }
,
{
  "is_managed" : "true",
  "guid" : "5B93611B-6FF0-4343-9D40-3FBB0837BC10",
  "token" : "0x00000",
  "native_offset" : "0x0",
  "filename" : "mscorlib.dll",
  "sizeofimage" : "0x470000",
  "timestamp" : "0xcdd9381c",
  "il_offset" : "0x00000"
 }
,
{
  "is_managed" : "true",
  "guid" : "5B93611B-6FF0-4343-9D40-3FBB0837BC10",
  "token" : "0x6001f5d",
  "native_offset" : "0x0",
  "filename" : "mscorlib.dll",
  "sizeofimage" : "0x470000",
  "timestamp" : "0xcdd9381c",
  "il_offset" : "0x0002f"
 }
,
{
  "is_managed" : "true",
  "guid" : "5B93611B-6FF0-4343-9D40-3FBB0837BC10",
  "token" : "0x6001f50",
  "native_offset" : "0x0",
  "filename" : "mscorlib.dll",
  "sizeofimage" : "0x470000",
  "timestamp" : "0xcdd9381c",
  "il_offset" : "0x0000e"
 }
,
{
  "is_managed" : "true",
  "guid" : "5B93611B-6FF0-4343-9D40-3FBB0837BC10",
  "token" : "0x6001f52",
  "native_offset" : "0x0",
  "filename" : "mscorlib.dll",
  "sizeofimage" : "0x470000",
  "timestamp" : "0xcdd9381c",
  "il_offset" : "0x00000"
 }
,
{
  "is_managed" : "true",
  "guid" : "5B93611B-6FF0-4343-9D40-3FBB0837BC10",
  "token" : "0x6001ea2",
  "native_offset" : "0x0",
  "filename" : "mscorlib.dll",
  "sizeofimage" : "0x470000",
  "timestamp" : "0xcdd9381c",
  "il_offset" : "0x0001d"
 }
,
{
  "is_managed" : "true",
  "guid" : "5B93611B-6FF0-4343-9D40-3FBB0837BC10",
  "token" : "0x6001ea1",
  "native_offset" : "0x0",
  "filename" : "mscorlib.dll",
  "sizeofimage" : "0x470000",
  "timestamp" : "0xcdd9381c",
  "il_offset" : "0x000d9"
 }
,
{
  "is_managed" : "true",
  "guid" : "56B59C73-3E00-4375-8D92-23398C020E5C",
  "token" : "0x6003fe8",
  "native_offset" : "0x0",
  "filename" : "System.dll",
  "sizeofimage" : "0x29a000",
  "timestamp" : "0xb03d23c3",
  "il_offset" : "0x00067"
 }
,
{
  "is_managed" : "true",
  "guid" : "56B59C73-3E00-4375-8D92-23398C020E5C",
  "token" : "0x6003fe7",
  "native_offset" : "0x0",
  "filename" : "System.dll",
  "sizeofimage" : "0x29a000",
  "timestamp" : "0xb03d23c3",
  "il_offset" : "0x00006"
 }
,
{
  "is_managed" : "true",
  "guid" : "56B59C73-3E00-4375-8D92-23398C020E5C",
  "token" : "0x6003fe3",
  "native_offset" : "0x0",
  "filename" : "System.dll",
  "sizeofimage" : "0x29a000",
  "timestamp" : "0xb03d23c3",
  "il_offset" : "0x00000"
 }
,
{
  "is_managed" : "true",
  "guid" : "A2DD1524-8A25-411E-914A-F2A2C82FB63F",
  "token" : "0x6001043",
  "native_offset" : "0x0",
  "filename" : "Burst.Compiler.IL.dll",
  "sizeofimage" : "0x188000",
  "timestamp" : "0xe06db050",
  "il_offset" : "0x000c9"
 }
,
{
  "is_managed" : "true",
  "guid" : "5B93611B-6FF0-4343-9D40-3FBB0837BC10",
  "token" : "0x6001f7d",
  "native_offset" : "0x0",
  "filename" : "mscorlib.dll",
  "sizeofimage" : "0x470000",
  "timestamp" : "0xcdd9381c",
  "il_offset" : "0x00014"
 }
,
{
  "is_managed" : "true",
  "guid" : "5B93611B-6FF0-4343-9D40-3FBB0837BC10",
  "token" : "0x6001f25",
  "native_offset" : "0x0",
  "filename" : "mscorlib.dll",
  "sizeofimage" : "0x470000",
  "timestamp" : "0xcdd9381c",
  "il_offset" : "0x00071"
 }
,
{
  "is_managed" : "true",
  "guid" : "5B93611B-6FF0-4343-9D40-3FBB0837BC10",
  "token" : "0x6001f23",
  "native_offset" : "0x0",
  "filename" : "mscorlib.dll",
  "sizeofimage" : "0x470000",
  "timestamp" : "0xcdd9381c",
  "il_offset" : "0x00000"
 }
,
{
  "is_managed" : "true",
  "guid" : "5B93611B-6FF0-4343-9D40-3FBB0837BC10",
  "token" : "0x6001f22",
  "native_offset" : "0x0",
  "filename" : "mscorlib.dll",
  "sizeofimage" : "0x470000",
  "timestamp" : "0xcdd9381c",
  "il_offset" : "0x0002b"
 }
,
{
  "is_managed" : "true",
  "guid" : "5B93611B-6FF0-4343-9D40-3FBB0837BC10",
  "token" : "0x6001f7f",
  "native_offset" : "0x0",
  "filename" : "mscorlib.dll",
  "sizeofimage" : "0x470000",
  "timestamp" : "0xcdd9381c",
  "il_offset" : "0x00008"
 }
,
{
  "is_managed" : "true",
  "guid" : "5B93611B-6FF0-4343-9D40-3FBB0837BC10",
  "token" : "0x00000",
  "native_offset" : "0x0",
  "filename" : "mscorlib.dll",
  "sizeofimage" : "0x470000",
  "timestamp" : "0xcdd9381c",
  "il_offset" : "0x00065"
 }

],
"unmanaged_frames" : [
{
"is_managed" : "false",
"native_address" : "0x15f3a8286",
"native_offset" : "0x00000"
}
,
{
"is_managed" : "false",
"native_address" : "0x15f501378",
"native_offset" : "0x00000"
}
,
{
"is_managed" : "false",
"native_address" : "0x15f5016b2",
"native_offset" : "0x00000"
}
,
{
"is_managed" : "false",
"native_address" : "0x15f501469",
"native_offset" : "0x00000"
}
,
{
"is_managed" : "false",
"native_address" : "0x15f405b4d",
"native_offset" : "0x00000"
}
,
{
"is_managed" : "false",
"native_address" : "0x7ff81de16dfd",
"native_offset" : "0x00000"
}
,
{
"is_managed" : "false",
"native_address" : "0xbbba",
"native_offset" : "0x00000"
}
,
{
"is_managed" : "false",
"native_address" : "0x15f54fee8",
"native_offset" : "0x00000"
}
,
{
"is_managed" : "false",
"native_address" : "0x15f50c3cd",
"native_offset" : "0x00000"
}
,
{
"is_managed" : "false",
"native_address" : "0x15f50c22f",
"native_offset" : "0x00000"
}
,
{
"is_managed" : "false",
"native_address" : "0x15f53cad4",
"native_offset" : "0x00000"
}
,
{
"is_managed" : "false",
"native_address" : "0x15f4a6693",
"native_offset" : "0x00000"
}
,
{
"is_managed" : "true",
"guid" : "5B93611B-6FF0-4343-9D40-3FBB0837BC10",
"token" : "0x00000",
"native_offset" : "0x0",
"filename" : "mscorlib.dll",
"sizeofimage" : "0x470000",
"timestamp" : "0xcdd9381c",
"il_offset" : "0x00000"
}
,
{
"is_managed" : "true",
"guid" : "5B93611B-6FF0-4343-9D40-3FBB0837BC10",
"token" : "0x6001f50",
"native_offset" : "0x0",
"filename" : "mscorlib.dll",
"sizeofimage" : "0x470000",
"timestamp" : "0xcdd9381c",
"il_offset" : "0x00000"
}
,
{
"is_managed" : "true",
"guid" : "56B59C73-3E00-4375-8D92-23398C020E5C",
"token" : "0x6003fe8",
"native_offset" : "0x0",
"filename" : "System.dll",
"sizeofimage" : "0x29a000",
"timestamp" : "0xb03d23c3",
"il_offset" : "0x00000"
}
,
{
"is_managed" : "true",
"guid" : "56B59C73-3E00-4375-8D92-23398C020E5C",
"token" : "0x6003fe7",
"native_offset" : "0x0",
"filename" : "System.dll",
"sizeofimage" : "0x29a000",
"timestamp" : "0xb03d23c3",
"il_offset" : "0x00000"
}
,
{
"is_managed" : "true",
"guid" : "5B93611B-6FF0-4343-9D40-3FBB0837BC10",
"token" : "0x6001f7d",
"native_offset" : "0x0",
"filename" : "mscorlib.dll",
"sizeofimage" : "0x470000",
"timestamp" : "0xcdd9381c",
"il_offset" : "0x00000"
}
,
{
"is_managed" : "true",
"guid" : "5B93611B-6FF0-4343-9D40-3FBB0837BC10",
"token" : "0x6001f23",
"native_offset" : "0x0",
"filename" : "mscorlib.dll",
"sizeofimage" : "0x470000",
"timestamp" : "0xcdd9381c",
"il_offset" : "0x00000"
}
,
{
"is_managed" : "false",
"native_address" : "0x15f32bc8c",
"native_offset" : "0x00000"
}
,
{
"is_managed" : "false",
"native_address" : "0x15f4e12ef",
"native_offset" : "0x00000"
}
,
{
"is_managed" : "false",
"native_address" : "0x15f4e2df9",
"native_offset" : "0x00000"
}
,
{
"is_managed" : "false",
"native_address" : "0x15f502194",
"native_offset" : "0x00000"
}
,
{
"is_managed" : "false",
"native_address" : "0x15f501f65",
"native_offset" : "0x00000"
}
,
{
"is_managed" : "false",
"native_address" : "0x15f57f319",
"native_offset" : "0x00000"
}
,
{
"is_managed" : "false",
"native_address" : "0x15f57f2b1",
"native_offset" : "0x00000"
}
,
{
"is_managed" : "false",
"native_address" : "0x7ff81de014e1",
"native_offset" : "0x00000"
}
,
{
"is_managed" : "false",
"native_address" : "0x7ff81ddfcf6b",
"native_offset" : "0x00000"
}

]
},
{
"is_managed" : true,
"offset_free_hash" : "0xbaa0c96f5",
"offset_rich_hash" : "0xbaa0c9ab6",
"crashed" : false,
"native_thread_id" : "0x70000ea4e000",
"thread_info_addr" : "0x7fae3ec86a00",
"thread_name" : "Burst-CompilerThread-7",
"ctx" : {
"IP" : "0x7ff81ddc73ea",
"SP" : "0x70000ea4cbb8",
"BP" : "0x70000ea4cc60"
},
"managed_frames" : [
{
"is_managed" : "false",
"native_address" : "unregistered"
}
,
{
"is_managed" : "true",
"guid" : "5B93611B-6FF0-4343-9D40-3FBB0837BC10",
"token" : "0x00000",
"native_offset" : "0x0",
"filename" : "mscorlib.dll",
"sizeofimage" : "0x470000",
"timestamp" : "0xcdd9381c",
"il_offset" : "0x00000"
}
,
{
"is_managed" : "true",
"guid" : "5B93611B-6FF0-4343-9D40-3FBB0837BC10",
"token" : "0x60020b3",
"native_offset" : "0x0",
"filename" : "mscorlib.dll",
"sizeofimage" : "0x470000",
"timestamp" : "0xcdd9381c",
"il_offset" : "0x000c7"
}
,
{
"is_managed" : "true",
"guid" : "5B93611B-6FF0-4343-9D40-3FBB0837BC10",
"token" : "0x60020a5",
"native_offset" : "0x0",
"filename" : "mscorlib.dll",
"sizeofimage" : "0x470000",
"timestamp" : "0xcdd9381c",
"il_offset" : "0x000a1"
}
,
{
"is_managed" : "true",
"guid" : "5B93611B-6FF0-4343-9D40-3FBB0837BC10",
"token" : "0x60020a9",
"native_offset" : "0x0",
"filename" : "mscorlib.dll",
"sizeofimage" : "0x470000",
"timestamp" : "0xcdd9381c",
"il_offset" : "0x00000"
}
,
{
"is_managed" : "true",
"guid" : "56B59C73-3E00-4375-8D92-23398C020E5C",
"token" : "0x6003ffa",
"native_offset" : "0x0",
"filename" : "System.dll",
"sizeofimage" : "0x29a000",
"timestamp" : "0xb03d23c3",
"il_offset" : "0x0006e"
}
,
{
"is_managed" : "true",
"guid" : "56B59C73-3E00-4375-8D92-23398C020E5C",
"token" : "0x6003ff9",
"native_offset" : "0x0",
"filename" : "System.dll",
"sizeofimage" : "0x29a000",
"timestamp" : "0xb03d23c3",
"il_offset" : "0x0003c"
}
,
{
"is_managed" : "true",
"guid" : "56B59C73-3E00-4375-8D92-23398C020E5C",
"token" : "0x6003ff4",
"native_offset" : "0x0",
"filename" : "System.dll",
"sizeofimage" : "0x29a000",
"timestamp" : "0xb03d23c3",
"il_offset" : "0x00000"
}
,
{
"is_managed" : "true",
"guid" : "A2DD1524-8A25-411E-914A-F2A2C82FB63F",
"token" : "0x6000b35",
"native_offset" : "0x0",
"filename" : "Burst.Compiler.IL.dll",
"sizeofimage" : "0x188000",
"timestamp" : "0xe06db050",
"il_offset" : "0x00024"
}
,
{
"is_managed" : "true",
"guid" : "A2DD1524-8A25-411E-914A-F2A2C82FB63F",
"token" : "0x6000b9c",
"native_offset" : "0x0",
"filename" : "Burst.Compiler.IL.dll",
"sizeofimage" : "0x188000",
"timestamp" : "0xe06db050",
"il_offset" : "0x0006e"
}
,
{
"is_managed" : "true",
"guid" : "5B93611B-6FF0-4343-9D40-3FBB0837BC10",
"token" : "0x6001f7d",
"native_offset" : "0x0",
"filename" : "mscorlib.dll",
"sizeofimage" : "0x470000",
"timestamp" : "0xcdd9381c",
"il_offset" : "0x00014"
}
,
{
"is_managed" : "true",
"guid" : "5B93611B-6FF0-4343-9D40-3FBB0837BC10",
"token" : "0x6001f25",
"native_offset" : "0x0",
"filename" : "mscorlib.dll",
"sizeofimage" : "0x470000",
"timestamp" : "0xcdd9381c",
"il_offset" : "0x00071"
}
,
{
"is_managed" : "true",
"guid" : "5B93611B-6FF0-4343-9D40-3FBB0837BC10",
"token" : "0x6001f23",
"native_offset" : "0x0",
"filename" : "mscorlib.dll",
"sizeofimage" : "0x470000",
"timestamp" : "0xcdd9381c",
"il_offset" : "0x00000"
}
,
{
"is_managed" : "true",
"guid" : "5B93611B-6FF0-4343-9D40-3FBB0837BC10",
"token" : "0x6001f22",
"native_offset" : "0x0",
"filename" : "mscorlib.dll",
"sizeofimage" : "0x470000",
"timestamp" : "0xcdd9381c",
"il_offset" : "0x0002b"
}
,
{
"is_managed" : "true",
"guid" : "5B93611B-6FF0-4343-9D40-3FBB0837BC10",
"token" : "0x6001f7f",
"native_offset" : "0x0",
"filename" : "mscorlib.dll",
"sizeofimage" : "0x470000",
"timestamp" : "0xcdd9381c",
"il_offset" : "0x00008"
}
,
{
"is_managed" : "true",
"guid" : "5B93611B-6FF0-4343-9D40-3FBB0837BC10",
"token" : "0x00000",
"native_offset" : "0x0",
"filename" : "mscorlib.dll",
"sizeofimage" : "0x470000",
"timestamp" : "0xcdd9381c",
"il_offset" : "0x00065"
}

],
"unmanaged_frames" : [
{
"is_managed" : "false",
"native_address" : "0x15f3a8286",
"native_offset" : "0x00000"
}
,
{
"is_managed" : "false",
"native_address" : "0x15f501378",
"native_offset" : "0x00000"
}
,
{
"is_managed" : "false",
"native_address" : "0x15f5016b2",
"native_offset" : "0x00000"
}
,
{
"is_managed" : "false",
"native_address" : "0x15f501469",
"native_offset" : "0x00000"
}
,
{
"is_managed" : "false",
"native_address" : "0x15f405b4d",
"native_offset" : "0x00000"
}
,
{
"is_managed" : "false",
"native_address" : "0x7ff81de16dfd",
"native_offset" : "0x00000"
}
,
{
"is_managed" : "false",
"native_address" : "0x7fae39cd6d60",
"native_offset" : "0x00000"
}
,
{
"is_managed" : "false",
"native_address" : "0x15f54fee8",
"native_offset" : "0x00000"
}
,
{
"is_managed" : "false",
"native_address" : "0x15f50cd08",
"native_offset" : "0x00000"
}
,
{
"is_managed" : "false",
"native_address" : "0x15f50c9ae",
"native_offset" : "0x00000"
}
,
{
"is_managed" : "false",
"native_address" : "0x15f4fcb9a",
"native_offset" : "0x00000"
}
,
{
"is_managed" : "false",
"native_address" : "0x15f4a7dca",
"native_offset" : "0x00000"
}
,
{
"is_managed" : "true",
"guid" : "5B93611B-6FF0-4343-9D40-3FBB0837BC10",
"token" : "0x00000",
"native_offset" : "0x0",
"filename" : "mscorlib.dll",
"sizeofimage" : "0x470000",
"timestamp" : "0xcdd9381c",
"il_offset" : "0x00000"
}
,
{
"is_managed" : "true",
"guid" : "5B93611B-6FF0-4343-9D40-3FBB0837BC10",
"token" : "0x60020a5",
"native_offset" : "0x0",
"filename" : "mscorlib.dll",
"sizeofimage" : "0x470000",
"timestamp" : "0xcdd9381c",
"il_offset" : "0x00000"
}

]
},
{
"is_managed" : false,
"offset_free_hash" : "0x0",
"offset_rich_hash" : "0x0",
"crashed" : false,
"native_thread_id" : "0x70000f0e3000",
"thread_info_addr" : "0x7fae3f5e5000",
"thread_name" : "Thread Pool I/O Selector",
"ctx" : {
"IP" : "0x7ff81ddccd5a",
"SP" : "0x70000f0e2b78",
"BP" : "0x70000f0e2d50"
},
"unmanaged_frames" : [
{
"is_managed" : "false",
"native_address" : "0x15f3a8286",
"native_offset" : "0x00000"
}
,
{
"is_managed" : "false",
"native_address" : "0x15f501378",
"native_offset" : "0x00000"
}
,
{
"is_managed" : "false",
"native_address" : "0x15f5016b2",
"native_offset" : "0x00000"
}
,
{
"is_managed" : "false",
"native_address" : "0x15f501469",
"native_offset" : "0x00000"
}
,
{
"is_managed" : "false",
"native_address" : "0x15f405b4d",
"native_offset" : "0x00000"
}
,
{
"is_managed" : "false",
"native_address" : "0x7ff81de16dfd",
"native_offset" : "0x00000"
}
,
{
"is_managed" : "false",
"native_address" : "0x15f4c4cc2",
"native_offset" : "0x00000"
}
,
{
"is_managed" : "false",
"native_address" : "0x15f50628c",
"native_offset" : "0x00000"
}
,
{
"is_managed" : "false",
"native_address" : "0x15f505d15",
"native_offset" : "0x00000"
}
,
{
"is_managed" : "false",
"native_address" : "0x15f5020c0",
"native_offset" : "0x00000"
}
,
{
"is_managed" : "false",
"native_address" : "0x15f501f65",
"native_offset" : "0x00000"
}
,
{
"is_managed" : "false",
"native_address" : "0x15f57f319",
"native_offset" : "0x00000"
}
,
{
"is_managed" : "false",
"native_address" : "0x15f57f2b1",
"native_offset" : "0x00000"
}
,
{
"is_managed" : "false",
"native_address" : "0x7ff81de014e1",
"native_offset" : "0x00000"
}
,
{
"is_managed" : "false",
"native_address" : "0x7ff81ddfcf6b",
"native_offset" : "0x00000"
}

]
},
{
"is_managed" : true,
"offset_free_hash" : "0xbaa0c96f5",
"offset_rich_hash" : "0xbaa0c9ab6",
"crashed" : false,
"native_thread_id" : "0x70000e84b000",
"thread_info_addr" : "0x7fae3f106000",
"thread_name" : "Burst-CompilerThread-6",
"ctx" : {
"IP" : "0x7ff81ddc73ea",
"SP" : "0x70000e849bb8",
"BP" : "0x70000e849c60"
},
"managed_frames" : [
{
"is_managed" : "false",
"native_address" : "unregistered"
}
,
{
"is_managed" : "true",
"guid" : "5B93611B-6FF0-4343-9D40-3FBB0837BC10",
"token" : "0x00000",
"native_offset" : "0x0",
"filename" : "mscorlib.dll",
"sizeofimage" : "0x470000",
"timestamp" : "0xcdd9381c",
"il_offset" : "0x00000"
}
,
{
"is_managed" : "true",
"guid" : "5B93611B-6FF0-4343-9D40-3FBB0837BC10",
"token" : "0x60020b3",
"native_offset" : "0x0",
"filename" : "mscorlib.dll",
"sizeofimage" : "0x470000",
"timestamp" : "0xcdd9381c",
"il_offset" : "0x000c7"
}
,
{
"is_managed" : "true",
"guid" : "5B93611B-6FF0-4343-9D40-3FBB0837BC10",
"token" : "0x60020a5",
"native_offset" : "0x0",
"filename" : "mscorlib.dll",
"sizeofimage" : "0x470000",
"timestamp" : "0xcdd9381c",
"il_offset" : "0x000a1"
}
,
{
"is_managed" : "true",
"guid" : "5B93611B-6FF0-4343-9D40-3FBB0837BC10",
"token" : "0x60020a9",
"native_offset" : "0x0",
"filename" : "mscorlib.dll",
"sizeofimage" : "0x470000",
"timestamp" : "0xcdd9381c",
"il_offset" : "0x00000"
}
,
{
"is_managed" : "true",
"guid" : "56B59C73-3E00-4375-8D92-23398C020E5C",
"token" : "0x6003ffa",
"native_offset" : "0x0",
"filename" : "System.dll",
"sizeofimage" : "0x29a000",
"timestamp" : "0xb03d23c3",
"il_offset" : "0x0006e"
}
,
{
"is_managed" : "true",
"guid" : "56B59C73-3E00-4375-8D92-23398C020E5C",
"token" : "0x6003ff9",
"native_offset" : "0x0",
"filename" : "System.dll",
"sizeofimage" : "0x29a000",
"timestamp" : "0xb03d23c3",
"il_offset" : "0x0003c"
}
,
{
"is_managed" : "true",
"guid" : "56B59C73-3E00-4375-8D92-23398C020E5C",
"token" : "0x6003ff4",
"native_offset" : "0x0",
"filename" : "System.dll",
"sizeofimage" : "0x29a000",
"timestamp" : "0xb03d23c3",
"il_offset" : "0x00000"
}
,
{
"is_managed" : "true",
"guid" : "A2DD1524-8A25-411E-914A-F2A2C82FB63F",
"token" : "0x6000b35",
"native_offset" : "0x0",
"filename" : "Burst.Compiler.IL.dll",
"sizeofimage" : "0x188000",
"timestamp" : "0xe06db050",
"il_offset" : "0x00024"
}
,
{
"is_managed" : "true",
"guid" : "A2DD1524-8A25-411E-914A-F2A2C82FB63F",
"token" : "0x6000b9c",
"native_offset" : "0x0",
"filename" : "Burst.Compiler.IL.dll",
"sizeofimage" : "0x188000",
"timestamp" : "0xe06db050",
"il_offset" : "0x0006e"
}
,
{
"is_managed" : "true",
"guid" : "5B93611B-6FF0-4343-9D40-3FBB0837BC10",
"token" : "0x6001f7d",
"native_offset" : "0x0",
"filename" : "mscorlib.dll",
"sizeofimage" : "0x470000",
"timestamp" : "0xcdd9381c",
"il_offset" : "0x00014"
}
,
{
"is_managed" : "true",
"guid" : "5B93611B-6FF0-4343-9D40-3FBB0837BC10",
"token" : "0x6001f25",
"native_offset" : "0x0",
"filename" : "mscorlib.dll",
"sizeofimage" : "0x470000",
"timestamp" : "0xcdd9381c",
"il_offset" : "0x00071"
}
,
{
"is_managed" : "true",
"guid" : "5B93611B-6FF0-4343-9D40-3FBB0837BC10",
"token" : "0x6001f23",
"native_offset" : "0x0",
"filename" : "mscorlib.dll",
"sizeofimage" : "0x470000",
"timestamp" : "0xcdd9381c",
"il_offset" : "0x00000"
}
,
{
"is_managed" : "true",
"guid" : "5B93611B-6FF0-4343-9D40-3FBB0837BC10",
"token" : "0x6001f22",
"native_offset" : "0x0",
"filename" : "mscorlib.dll",
"sizeofimage" : "0x470000",
"timestamp" : "0xcdd9381c",
"il_offset" : "0x0002b"
}
,
{
"is_managed" : "true",
"guid" : "5B93611B-6FF0-4343-9D40-3FBB0837BC10",
"token" : "0x6001f7f",
"native_offset" : "0x0",
"filename" : "mscorlib.dll",
"sizeofimage" : "0x470000",
"timestamp" : "0xcdd9381c",
"il_offset" : "0x00008"
}
,
{
"is_managed" : "true",
"guid" : "5B93611B-6FF0-4343-9D40-3FBB0837BC10",
"token" : "0x00000",
"native_offset" : "0x0",
"filename" : "mscorlib.dll",
"sizeofimage" : "0x470000",
"timestamp" : "0xcdd9381c",
"il_offset" : "0x00065"
}

],
"unmanaged_frames" : [
{
"is_managed" : "false",
"native_address" : "0x15f3a8286",
"native_offset" : "0x00000"
}
,
{
"is_managed" : "false",
"native_address" : "0x15f501378",
"native_offset" : "0x00000"
}
,
{
"is_managed" : "false",
"native_address" : "0x15f5016b2",
"native_offset" : "0x00000"
}
,
{
"is_managed" : "false",
"native_address" : "0x15f501469",
"native_offset" : "0x00000"
}
,
{
"is_managed" : "false",
"native_address" : "0x15f405b4d",
"native_offset" : "0x00000"
}
,
{
"is_managed" : "false",
"native_address" : "0x7ff81de16dfd",
"native_offset" : "0x00000"
}
,
{
"is_managed" : "false",
"native_address" : "0x7fae39ea5020",
"native_offset" : "0x00000"
}
,
{
"is_managed" : "false",
"native_address" : "0x15f54fee8",
"native_offset" : "0x00000"
}
,
{
"is_managed" : "false",
"native_address" : "0x15f50cd08",
"native_offset" : "0x00000"
}
,
{
"is_managed" : "false",
"native_address" : "0x15f50c9ae",
"native_offset" : "0x00000"
}
,
{
"is_managed" : "false",
"native_address" : "0x15f4fcb9a",
"native_offset" : "0x00000"
}
,
{
"is_managed" : "false",
"native_address" : "0x15f4a7dca",
"native_offset" : "0x00000"
}
,
{
"is_managed" : "true",
"guid" : "5B93611B-6FF0-4343-9D40-3FBB0837BC10",
"token" : "0x00000",
"native_offset" : "0x0",
"filename" : "mscorlib.dll",
"sizeofimage" : "0x470000",
"timestamp" : "0xcdd9381c",
"il_offset" : "0x00000"
}
,
{
"is_managed" : "true",
"guid" : "5B93611B-6FF0-4343-9D40-3FBB0837BC10",
"token" : "0x60020a5",
"native_offset" : "0x0",
"filename" : "mscorlib.dll",
"sizeofimage" : "0x470000",
"timestamp" : "0xcdd9381c",
"il_offset" : "0x00000"
}

]
},
{
"is_managed" : true,
"offset_free_hash" : "0xbaa0c96f5",
"offset_rich_hash" : "0xbaa0c9ab6",
"crashed" : false,
"native_thread_id" : "0x70000e648000",
"thread_info_addr" : "0x7fae3ab71400",
"thread_name" : "Burst-CompilerThread-5",
"ctx" : {
"IP" : "0x7ff81ddc73ea",
"SP" : "0x70000e646bb8",
"BP" : "0x70000e646c60"
},
"managed_frames" : [
{
"is_managed" : "false",
"native_address" : "unregistered"
}
,
{
"is_managed" : "true",
"guid" : "5B93611B-6FF0-4343-9D40-3FBB0837BC10",
"token" : "0x00000",
"native_offset" : "0x0",
"filename" : "mscorlib.dll",
"sizeofimage" : "0x470000",
"timestamp" : "0xcdd9381c",
"il_offset" : "0x00000"
}
,
{
"is_managed" : "true",
"guid" : "5B93611B-6FF0-4343-9D40-3FBB0837BC10",
"token" : "0x60020b3",
"native_offset" : "0x0",
"filename" : "mscorlib.dll",
"sizeofimage" : "0x470000",
"timestamp" : "0xcdd9381c",
"il_offset" : "0x000c7"
}
,
{
"is_managed" : "true",
"guid" : "5B93611B-6FF0-4343-9D40-3FBB0837BC10",
"token" : "0x60020a5",
"native_offset" : "0x0",
"filename" : "mscorlib.dll",
"sizeofimage" : "0x470000",
"timestamp" : "0xcdd9381c",
"il_offset" : "0x000a1"
}
,
{
"is_managed" : "true",
"guid" : "5B93611B-6FF0-4343-9D40-3FBB0837BC10",
"token" : "0x60020a9",
"native_offset" : "0x0",
"filename" : "mscorlib.dll",
"sizeofimage" : "0x470000",
"timestamp" : "0xcdd9381c",
"il_offset" : "0x00000"
}
,
{
"is_managed" : "true",
"guid" : "56B59C73-3E00-4375-8D92-23398C020E5C",
"token" : "0x6003ffa",
"native_offset" : "0x0",
"filename" : "System.dll",
"sizeofimage" : "0x29a000",
"timestamp" : "0xb03d23c3",
"il_offset" : "0x0006e"
}
,
{
"is_managed" : "true",
"guid" : "56B59C73-3E00-4375-8D92-23398C020E5C",
"token" : "0x6003ff9",
"native_offset" : "0x0",
"filename" : "System.dll",
"sizeofimage" : "0x29a000",
"timestamp" : "0xb03d23c3",
"il_offset" : "0x0003c"
}
,
{
"is_managed" : "true",
"guid" : "56B59C73-3E00-4375-8D92-23398C020E5C",
"token" : "0x6003ff4",
"native_offset" : "0x0",
"filename" : "System.dll",
"sizeofimage" : "0x29a000",
"timestamp" : "0xb03d23c3",
"il_offset" : "0x00000"
}
,
{
"is_managed" : "true",
"guid" : "A2DD1524-8A25-411E-914A-F2A2C82FB63F",
"token" : "0x6000b35",
"native_offset" : "0x0",
"filename" : "Burst.Compiler.IL.dll",
"sizeofimage" : "0x188000",
"timestamp" : "0xe06db050",
"il_offset" : "0x00024"
}
,
{
"is_managed" : "true",
"guid" : "A2DD1524-8A25-411E-914A-F2A2C82FB63F",
"token" : "0x6000b9c",
"native_offset" : "0x0",
"filename" : "Burst.Compiler.IL.dll",
"sizeofimage" : "0x188000",
"timestamp" : "0xe06db050",
"il_offset" : "0x0006e"
}
,
{
"is_managed" : "true",
"guid" : "5B93611B-6FF0-4343-9D40-3FBB0837BC10",
"token" : "0x6001f7d",
"native_offset" : "0x0",
"filename" : "mscorlib.dll",
"sizeofimage" : "0x470000",
"timestamp" : "0xcdd9381c",
"il_offset" : "0x00014"
}
,
{
"is_managed" : "true",
"guid" : "5B93611B-6FF0-4343-9D40-3FBB0837BC10",
"token" : "0x6001f25",
"native_offset" : "0x0",
"filename" : "mscorlib.dll",
"sizeofimage" : "0x470000",
"timestamp" : "0xcdd9381c",
"il_offset" : "0x00071"
}
,
{
"is_managed" : "true",
"guid" : "5B93611B-6FF0-4343-9D40-3FBB0837BC10",
"token" : "0x6001f23",
"native_offset" : "0x0",
"filename" : "mscorlib.dll",
"sizeofimage" : "0x470000",
"timestamp" : "0xcdd9381c",
"il_offset" : "0x00000"
}
,
{
"is_managed" : "true",
"guid" : "5B93611B-6FF0-4343-9D40-3FBB0837BC10",
"token" : "0x6001f22",
"native_offset" : "0x0",
"filename" : "mscorlib.dll",
"sizeofimage" : "0x470000",
"timestamp" : "0xcdd9381c",
"il_offset" : "0x0002b"
}
,
{
"is_managed" : "true",
"guid" : "5B93611B-6FF0-4343-9D40-3FBB0837BC10",
"token" : "0x6001f7f",
"native_offset" : "0x0",
"filename" : "mscorlib.dll",
"sizeofimage" : "0x470000",
"timestamp" : "0xcdd9381c",
"il_offset" : "0x00008"
}
,
{
"is_managed" : "true",
"guid" : "5B93611B-6FF0-4343-9D40-3FBB0837BC10",
"token" : "0x00000",
"native_offset" : "0x0",
"filename" : "mscorlib.dll",
"sizeofimage" : "0x470000",
"timestamp" : "0xcdd9381c",
"il_offset" : "0x00065"
}

],
"unmanaged_frames" : [
{
"is_managed" : "false",
"native_address" : "0x15f3a8286",
"native_offset" : "0x00000"
}
,
{
"is_managed" : "false",
"native_address" : "0x15f501378",
"native_offset" : "0x00000"
}
,
{
"is_managed" : "false",
"native_address" : "0x15f5016b2",
"native_offset" : "0x00000"
}
,
{
"is_managed" : "false",
"native_address" : "0x15f501469",
"native_offset" : "0x00000"
}
,
{
"is_managed" : "false",
"native_address" : "0x15f405b4d",
"native_offset" : "0x00000"
}
,
{
"is_managed" : "false",
"native_address" : "0x7ff81de16dfd",
"native_offset" : "0x00000"
}
,
{
"is_managed" : "false",
"native_address" : "0x7fae39ced470",
"native_offset" : "0x00000"
}
,
{
"is_managed" : "false",
"native_address" : "0x15f54fee8",
"native_offset" : "0x00000"
}
,
{
"is_managed" : "false",
"native_address" : "0x15f50cd08",
"native_offset" : "0x00000"
}
,
{
"is_managed" : "false",
"native_address" : "0x15f50c9ae",
"native_offset" : "0x00000"
}
,
{
"is_managed" : "false",
"native_address" : "0x15f4fcb9a",
"native_offset" : "0x00000"
}
,
{
"is_managed" : "false",
"native_address" : "0x15f4a7dca",
"native_offset" : "0x00000"
}
,
{
"is_managed" : "true",
"guid" : "5B93611B-6FF0-4343-9D40-3FBB0837BC10",
"token" : "0x00000",
"native_offset" : "0x0",
"filename" : "mscorlib.dll",
"sizeofimage" : "0x470000",
"timestamp" : "0xcdd9381c",
"il_offset" : "0x00000"
}
,
{
"is_managed" : "true",
"guid" : "5B93611B-6FF0-4343-9D40-3FBB0837BC10",
"token" : "0x60020a5",
"native_offset" : "0x0",
"filename" : "mscorlib.dll",
"sizeofimage" : "0x470000",
"timestamp" : "0xcdd9381c",
"il_offset" : "0x00000"
}

]
},
{
"is_managed" : false,
"offset_free_hash" : "0x0",
"offset_rich_hash" : "0x0",
"crashed" : false,
"native_thread_id" : "0x70000d83c000",
"thread_info_addr" : "0x7fae3f5e0800",
"thread_name" : "tid_2bd0f",
"ctx" : {
"IP" : "0x7ff81ddc49b6",
"SP" : "0x70000d83bd88",
"BP" : "0x70000d83bda0"
},
"unmanaged_frames" : [
{
"is_managed" : "false",
"native_address" : "0x15f3a8286",
"native_offset" : "0x00000"
}
,
{
"is_managed" : "false",
"native_address" : "0x15f501378",
"native_offset" : "0x00000"
}
,
{
"is_managed" : "false",
"native_address" : "0x15f5016b2",
"native_offset" : "0x00000"
}
,
{
"is_managed" : "false",
"native_address" : "0x15f501469",
"native_offset" : "0x00000"
}
,
{
"is_managed" : "false",
"native_address" : "0x15f405b4d",
"native_offset" : "0x00000"
}
,
{
"is_managed" : "false",
"native_address" : "0x7ff81de16dfd",
"native_offset" : "0x00000"
}
,
{
"is_managed" : "false",
"native_address" : "0x10798c1f5",
"native_offset" : "0x00000"
}
,
{
"is_managed" : "false",
"native_address" : "0x7ff81dc4ac9d",
"native_offset" : "0x00000"
}
,
{
"is_managed" : "false",
"native_address" : "0x1085babc8",
"native_offset" : "0x00000"
}
,
{
"is_managed" : "false",
"native_address" : "0x105d3634a",
"native_offset" : "0x00000"
}
,
{
"is_managed" : "false",
"native_address" : "0x10614bf3d",
"native_offset" : "0x00000"
}
,
{
"is_managed" : "false",
"native_address" : "0x10614bec8",
"native_offset" : "0x00000"
}
,
{
"is_managed" : "false",
"native_address" : "0x1062ee24b",
"native_offset" : "0x00000"
}
,
{
"is_managed" : "false",
"native_address" : "0x7ff81de014e1",
"native_offset" : "0x00000"
}
,
{
"is_managed" : "false",
"native_address" : "0x7ff81ddfcf6b",
"native_offset" : "0x00000"
}

]
},
{
"is_managed" : true,
"offset_free_hash" : "0xbaa0c96f5",
"offset_rich_hash" : "0xbaa0c9ab6",
"crashed" : false,
"native_thread_id" : "0x70000e445000",
"thread_info_addr" : "0x7fae3ebb2200",
"thread_name" : "Burst-CompilerThread-4",
"ctx" : {
"IP" : "0x7ff81ddc73ea",
"SP" : "0x70000e443bb8",
"BP" : "0x70000e443c60"
},
"managed_frames" : [
{
"is_managed" : "false",
"native_address" : "unregistered"
}
,
{
"is_managed" : "true",
"guid" : "5B93611B-6FF0-4343-9D40-3FBB0837BC10",
"token" : "0x00000",
"native_offset" : "0x0",
"filename" : "mscorlib.dll",
"sizeofimage" : "0x470000",
"timestamp" : "0xcdd9381c",
"il_offset" : "0x00000"
}
,
{
"is_managed" : "true",
"guid" : "5B93611B-6FF0-4343-9D40-3FBB0837BC10",
"token" : "0x60020b3",
"native_offset" : "0x0",
"filename" : "mscorlib.dll",
"sizeofimage" : "0x470000",
"timestamp" : "0xcdd9381c",
"il_offset" : "0x000c7"
}
,
{
"is_managed" : "true",
"guid" : "5B93611B-6FF0-4343-9D40-3FBB0837BC10",
"token" : "0x60020a5",
"native_offset" : "0x0",
"filename" : "mscorlib.dll",
"sizeofimage" : "0x470000",
"timestamp" : "0xcdd9381c",
"il_offset" : "0x000a1"
}
,
{
"is_managed" : "true",
"guid" : "5B93611B-6FF0-4343-9D40-3FBB0837BC10",
"token" : "0x60020a9",
"native_offset" : "0x0",
"filename" : "mscorlib.dll",
"sizeofimage" : "0x470000",
"timestamp" : "0xcdd9381c",
"il_offset" : "0x00000"
}
,
{
"is_managed" : "true",
"guid" : "56B59C73-3E00-4375-8D92-23398C020E5C",
"token" : "0x6003ffa",
"native_offset" : "0x0",
"filename" : "System.dll",
"sizeofimage" : "0x29a000",
"timestamp" : "0xb03d23c3",
"il_offset" : "0x0006e"
}
,
{
"is_managed" : "true",
"guid" : "56B59C73-3E00-4375-8D92-23398C020E5C",
"token" : "0x6003ff9",
"native_offset" : "0x0",
"filename" : "System.dll",
"sizeofimage" : "0x29a000",
"timestamp" : "0xb03d23c3",
"il_offset" : "0x0003c"
}
,
{
"is_managed" : "true",
"guid" : "56B59C73-3E00-4375-8D92-23398C020E5C",
"token" : "0x6003ff4",
"native_offset" : "0x0",
"filename" : "System.dll",
"sizeofimage" : "0x29a000",
"timestamp" : "0xb03d23c3",
"il_offset" : "0x00000"
}
,
{
"is_managed" : "true",
"guid" : "A2DD1524-8A25-411E-914A-F2A2C82FB63F",
"token" : "0x6000b35",
"native_offset" : "0x0",
"filename" : "Burst.Compiler.IL.dll",
"sizeofimage" : "0x188000",
"timestamp" : "0xe06db050",
"il_offset" : "0x00024"
}
,
{
"is_managed" : "true",
"guid" : "A2DD1524-8A25-411E-914A-F2A2C82FB63F",
"token" : "0x6000b9c",
"native_offset" : "0x0",
"filename" : "Burst.Compiler.IL.dll",
"sizeofimage" : "0x188000",
"timestamp" : "0xe06db050",
"il_offset" : "0x0006e"
}
,
{
"is_managed" : "true",
"guid" : "5B93611B-6FF0-4343-9D40-3FBB0837BC10",
"token" : "0x6001f7d",
"native_offset" : "0x0",
"filename" : "mscorlib.dll",
"sizeofimage" : "0x470000",
"timestamp" : "0xcdd9381c",
"il_offset" : "0x00014"
}
,
{
"is_managed" : "true",
"guid" : "5B93611B-6FF0-4343-9D40-3FBB0837BC10",
"token" : "0x6001f25",
"native_offset" : "0x0",
"filename" : "mscorlib.dll",
"sizeofimage" : "0x470000",
"timestamp" : "0xcdd9381c",
"il_offset" : "0x00071"
}
,
{
"is_managed" : "true",
"guid" : "5B93611B-6FF0-4343-9D40-3FBB0837BC10",
"token" : "0x6001f23",
"native_offset" : "0x0",
"filename" : "mscorlib.dll",
"sizeofimage" : "0x470000",
"timestamp" : "0xcdd9381c",
"il_offset" : "0x00000"
}
,
{
"is_managed" : "true",
"guid" : "5B93611B-6FF0-4343-9D40-3FBB0837BC10",
"token" : "0x6001f22",
"native_offset" : "0x0",
"filename" : "mscorlib.dll",
"sizeofimage" : "0x470000",
"timestamp" : "0xcdd9381c",
"il_offset" : "0x0002b"
}
,
{
"is_managed" : "true",
"guid" : "5B93611B-6FF0-4343-9D40-3FBB0837BC10",
"token" : "0x6001f7f",
"native_offset" : "0x0",
"filename" : "mscorlib.dll",
"sizeofimage" : "0x470000",
"timestamp" : "0xcdd9381c",
"il_offset" : "0x00008"
}
,
{
"is_managed" : "true",
"guid" : "5B93611B-6FF0-4343-9D40-3FBB0837BC10",
"token" : "0x00000",
"native_offset" : "0x0",
"filename" : "mscorlib.dll",
"sizeofimage" : "0x470000",
"timestamp" : "0xcdd9381c",
"il_offset" : "0x00065"
}

],
"unmanaged_frames" : [
{
"is_managed" : "false",
"native_address" : "0x15f3a8286",
"native_offset" : "0x00000"
}
,
{
"is_managed" : "false",
"native_address" : "0x15f501378",
"native_offset" : "0x00000"
}
,
{
"is_managed" : "false",
"native_address" : "0x15f5016b2",
"native_offset" : "0x00000"
}
,
{
"is_managed" : "false",
"native_address" : "0x15f501469",
"native_offset" : "0x00000"
}
,
{
"is_managed" : "false",
"native_address" : "0x15f405b4d",
"native_offset" : "0x00000"
}
,
{
"is_managed" : "false",
"native_address" : "0x7ff81de16dfd",
"native_offset" : "0x00000"
}
,
{
"is_managed" : "false",
"native_address" : "0x7fae3f382400",
"native_offset" : "0x00000"
}
,
{
"is_managed" : "false",
"native_address" : "0x15f54fee8",
"native_offset" : "0x00000"
}
,
{
"is_managed" : "false",
"native_address" : "0x15f50cd08",
"native_offset" : "0x00000"
}
,
{
"is_managed" : "false",
"native_address" : "0x15f50c9ae",
"native_offset" : "0x00000"
}
,
{
"is_managed" : "false",
"native_address" : "0x15f4fcb9a",
"native_offset" : "0x00000"
}
,
{
"is_managed" : "false",
"native_address" : "0x15f4a7dca",
"native_offset" : "0x00000"
}
,
{
"is_managed" : "true",
"guid" : "5B93611B-6FF0-4343-9D40-3FBB0837BC10",
"token" : "0x00000",
"native_offset" : "0x0",
"filename" : "mscorlib.dll",
"sizeofimage" : "0x470000",
"timestamp" : "0xcdd9381c",
"il_offset" : "0x00000"
}
,
{
"is_managed" : "true",
"guid" : "5B93611B-6FF0-4343-9D40-3FBB0837BC10",
"token" : "0x60020a5",
"native_offset" : "0x0",
"filename" : "mscorlib.dll",
"sizeofimage" : "0x470000",
"timestamp" : "0xcdd9381c",
"il_offset" : "0x00000"
}

]
},
{
"is_managed" : false,
"offset_free_hash" : "0x0",
"offset_rich_hash" : "0x0",
"crashed" : false,
"native_thread_id" : "0x70000cfa4000",
"thread_info_addr" : "0x7fae337bd800",
"thread_name" : "Debugger agent",
"ctx" : {
"IP" : "0x7ff81ddcb092",
"SP" : "0x70000cfa3ae8",
"BP" : "0x70000cfa3b20"
},
"unmanaged_frames" : [
{
"is_managed" : "false",
"native_address" : "0x15f3a8286",
"native_offset" : "0x00000"
}
,
{
"is_managed" : "false",
"native_address" : "0x15f501378",
"native_offset" : "0x00000"
}
,
{
"is_managed" : "false",
"native_address" : "0x15f5016b2",
"native_offset" : "0x00000"
}
,
{
"is_managed" : "false",
"native_address" : "0x15f501469",
"native_offset" : "0x00000"
}
,
{
"is_managed" : "false",
"native_address" : "0x15f405b4d",
"native_offset" : "0x00000"
}
,
{
"is_managed" : "false",
"native_address" : "0x7ff81de16dfd",
"native_offset" : "0x00000"
}
,
{
"is_managed" : "false",
"native_address" : "unregistered"
}
,
{
"is_managed" : "false",
"native_address" : "0x15f42f23a",
"native_offset" : "0x00000"
}
,
{
"is_managed" : "false",
"native_address" : "0x15f5020c0",
"native_offset" : "0x00000"
}
,
{
"is_managed" : "false",
"native_address" : "0x15f501f65",
"native_offset" : "0x00000"
}
,
{
"is_managed" : "false",
"native_address" : "0x15f57f319",
"native_offset" : "0x00000"
}
,
{
"is_managed" : "false",
"native_address" : "0x15f57f2b1",
"native_offset" : "0x00000"
}
,
{
"is_managed" : "false",
"native_address" : "0x7ff81de014e1",
"native_offset" : "0x00000"
}
,
{
"is_managed" : "false",
"native_address" : "0x7ff81ddfcf6b",
"native_offset" : "0x00000"
}

]
},
{
"is_managed" : false,
"offset_free_hash" : "0x0",
"offset_rich_hash" : "0x0",
"crashed" : true,
"native_thread_id" : "0x11105f600",
"thread_info_addr" : "0x7fae33ae4400",
"thread_name" : "tid_103",
"ctx" : {
"IP" : "0x7ff81dc79357",
"SP" : "0x7ff7ba6e5cb8",
"BP" : "0x7ff7ba6e5cf0"
}
},
{
"is_managed" : true,
"offset_free_hash" : "0xbaa0c96f5",
"offset_rich_hash" : "0xbaa0c9ab6",
"crashed" : false,
"native_thread_id" : "0x70000e242000",
"thread_info_addr" : "0x7fae3ec10600",
"thread_name" : "Burst-CompilerThread-3",
"ctx" : {
"IP" : "0x7ff81ddc73ea",
"SP" : "0x70000e240bb8",
"BP" : "0x70000e240c60"
},
"managed_frames" : [
{
"is_managed" : "false",
"native_address" : "unregistered"
}
,
{
"is_managed" : "true",
"guid" : "5B93611B-6FF0-4343-9D40-3FBB0837BC10",
"token" : "0x00000",
"native_offset" : "0x0",
"filename" : "mscorlib.dll",
"sizeofimage" : "0x470000",
"timestamp" : "0xcdd9381c",
"il_offset" : "0x00000"
}
,
{
"is_managed" : "true",
"guid" : "5B93611B-6FF0-4343-9D40-3FBB0837BC10",
"token" : "0x60020b3",
"native_offset" : "0x0",
"filename" : "mscorlib.dll",
"sizeofimage" : "0x470000",
"timestamp" : "0xcdd9381c",
"il_offset" : "0x000c7"
}
,
{
"is_managed" : "true",
"guid" : "5B93611B-6FF0-4343-9D40-3FBB0837BC10",
"token" : "0x60020a5",
"native_offset" : "0x0",
"filename" : "mscorlib.dll",
"sizeofimage" : "0x470000",
"timestamp" : "0xcdd9381c",
"il_offset" : "0x000a1"
}
,
{
"is_managed" : "true",
"guid" : "5B93611B-6FF0-4343-9D40-3FBB0837BC10",
"token" : "0x60020a9",
"native_offset" : "0x0",
"filename" : "mscorlib.dll",
"sizeofimage" : "0x470000",
"timestamp" : "0xcdd9381c",
"il_offset" : "0x00000"
}
,
{
"is_managed" : "true",
"guid" : "56B59C73-3E00-4375-8D92-23398C020E5C",
"token" : "0x6003ffa",
"native_offset" : "0x0",
"filename" : "System.dll",
"sizeofimage" : "0x29a000",
"timestamp" : "0xb03d23c3",
"il_offset" : "0x0006e"
}
,
{
"is_managed" : "true",
"guid" : "56B59C73-3E00-4375-8D92-23398C020E5C",
"token" : "0x6003ff9",
"native_offset" : "0x0",
"filename" : "System.dll",
"sizeofimage" : "0x29a000",
"timestamp" : "0xb03d23c3",
"il_offset" : "0x0003c"
}
,
{
"is_managed" : "true",
"guid" : "56B59C73-3E00-4375-8D92-23398C020E5C",
"token" : "0x6003ff4",
"native_offset" : "0x0",
"filename" : "System.dll",
"sizeofimage" : "0x29a000",
"timestamp" : "0xb03d23c3",
"il_offset" : "0x00000"
}
,
{
"is_managed" : "true",
"guid" : "A2DD1524-8A25-411E-914A-F2A2C82FB63F",
"token" : "0x6000b35",
"native_offset" : "0x0",
"filename" : "Burst.Compiler.IL.dll",
"sizeofimage" : "0x188000",
"timestamp" : "0xe06db050",
"il_offset" : "0x00024"
}
,
{
"is_managed" : "true",
"guid" : "A2DD1524-8A25-411E-914A-F2A2C82FB63F",
"token" : "0x6000b9c",
"native_offset" : "0x0",
"filename" : "Burst.Compiler.IL.dll",
"sizeofimage" : "0x188000",
"timestamp" : "0xe06db050",
"il_offset" : "0x0006e"
}
,
{
"is_managed" : "true",
"guid" : "5B93611B-6FF0-4343-9D40-3FBB0837BC10",
"token" : "0x6001f7d",
"native_offset" : "0x0",
"filename" : "mscorlib.dll",
"sizeofimage" : "0x470000",
"timestamp" : "0xcdd9381c",
"il_offset" : "0x00014"
}
,
{
"is_managed" : "true",
"guid" : "5B93611B-6FF0-4343-9D40-3FBB0837BC10",
"token" : "0x6001f25",
"native_offset" : "0x0",
"filename" : "mscorlib.dll",
"sizeofimage" : "0x470000",
"timestamp" : "0xcdd9381c",
"il_offset" : "0x00071"
}
,
{
"is_managed" : "true",
"guid" : "5B93611B-6FF0-4343-9D40-3FBB0837BC10",
"token" : "0x6001f23",
"native_offset" : "0x0",
"filename" : "mscorlib.dll",
"sizeofimage" : "0x470000",
"timestamp" : "0xcdd9381c",
"il_offset" : "0x00000"
}
,
{
"is_managed" : "true",
"guid" : "5B93611B-6FF0-4343-9D40-3FBB0837BC10",
"token" : "0x6001f22",
"native_offset" : "0x0",
"filename" : "mscorlib.dll",
"sizeofimage" : "0x470000",
"timestamp" : "0xcdd9381c",
"il_offset" : "0x0002b"
}
,
{
"is_managed" : "true",
"guid" : "5B93611B-6FF0-4343-9D40-3FBB0837BC10",
"token" : "0x6001f7f",
"native_offset" : "0x0",
"filename" : "mscorlib.dll",
"sizeofimage" : "0x470000",
"timestamp" : "0xcdd9381c",
"il_offset" : "0x00008"
}
,
{
"is_managed" : "true",
"guid" : "5B93611B-6FF0-4343-9D40-3FBB0837BC10",
"token" : "0x00000",
"native_offset" : "0x0",
"filename" : "mscorlib.dll",
"sizeofimage" : "0x470000",
"timestamp" : "0xcdd9381c",
"il_offset" : "0x00065"
}

],
"unmanaged_frames" : [
{
"is_managed" : "false",
"native_address" : "0x15f3a8286",
"native_offset" : "0x00000"
}
,
{
"is_managed" : "false",
"native_address" : "0x15f501378",
"native_offset" : "0x00000"
}
,
{
"is_managed" : "false",
"native_address" : "0x15f5016b2",
"native_offset" : "0x00000"
}
,
{
"is_managed" : "false",
"native_address" : "0x15f501469",
"native_offset" : "0x00000"
}
,
{
"is_managed" : "false",
"native_address" : "0x15f405b4d",
"native_offset" : "0x00000"
}
,
{
"is_managed" : "false",
"native_address" : "0x7ff81de16dfd",
"native_offset" : "0x00000"
}
,
{
"is_managed" : "false",
"native_address" : "0x7fae39cf0490",
"native_offset" : "0x00000"
}
,
{
"is_managed" : "false",
"native_address" : "0x15f54fee8",
"native_offset" : "0x00000"
}
,
{
"is_managed" : "false",
"native_address" : "0x15f50cd08",
"native_offset" : "0x00000"
}
,
{
"is_managed" : "false",
"native_address" : "0x15f50c9ae",
"native_offset" : "0x00000"
}
,
{
"is_managed" : "false",
"native_address" : "0x15f4fcb9a",
"native_offset" : "0x00000"
}
,
{
"is_managed" : "false",
"native_address" : "0x15f4a7dca",
"native_offset" : "0x00000"
}
,
{
"is_managed" : "true",
"guid" : "5B93611B-6FF0-4343-9D40-3FBB0837BC10",
"token" : "0x00000",
"native_offset" : "0x0",
"filename" : "mscorlib.dll",
"sizeofimage" : "0x470000",
"timestamp" : "0xcdd9381c",
"il_offset" : "0x00000"
}
,
{
"is_managed" : "true",
"guid" : "5B93611B-6FF0-4343-9D40-3FBB0837BC10",
"token" : "0x60020a5",
"native_offset" : "0x0",
"filename" : "mscorlib.dll",
"sizeofimage" : "0x470000",
"timestamp" : "0xcdd9381c",
"il_offset" : "0x00000"
}

]
},
{
"is_managed" : false,
"offset_free_hash" : "0x0",
"offset_rich_hash" : "0x0",
"crashed" : false,
"native_thread_id" : "0x70000cda1000",
"thread_info_addr" : "0x7fae33797800",
"thread_name" : "Finalizer",
"ctx" : {
"IP" : "0x7ff81ddc49b6",
"SP" : "0x70000cda0e18",
"BP" : "0x70000cda0e60"
},
"unmanaged_frames" : [
{
"is_managed" : "false",
"native_address" : "0x15f3a8286",
"native_offset" : "0x00000"
}
,
{
"is_managed" : "false",
"native_address" : "0x15f501378",
"native_offset" : "0x00000"
}
,
{
"is_managed" : "false",
"native_address" : "0x15f5016b2",
"native_offset" : "0x00000"
}
,
{
"is_managed" : "false",
"native_address" : "0x15f501469",
"native_offset" : "0x00000"
}
,
{
"is_managed" : "false",
"native_address" : "0x15f405b4d",
"native_offset" : "0x00000"
}
,
{
"is_managed" : "false",
"native_address" : "0x7ff81de16dfd",
"native_offset" : "0x00000"
}
,
{
"is_managed" : "false",
"native_address" : "unregistered"
}
,
{
"is_managed" : "false",
"native_address" : "0x15f5020c0",
"native_offset" : "0x00000"
}
,
{
"is_managed" : "false",
"native_address" : "0x15f501f65",
"native_offset" : "0x00000"
}
,
{
"is_managed" : "false",
"native_address" : "0x15f57f319",
"native_offset" : "0x00000"
}
,
{
"is_managed" : "false",
"native_address" : "0x15f57f2b1",
"native_offset" : "0x00000"
}
,
{
"is_managed" : "false",
"native_address" : "0x7ff81de014e1",
"native_offset" : "0x00000"
}
,
{
"is_managed" : "false",
"native_address" : "0x7ff81ddfcf6b",
"native_offset" : "0x00000"
}

]
}
]
}